{
  "nonDiplomat": {
    "description": "",
    "1-3": 900,
    "4": 950,
    "5": 1000,
    "6": 1050,
    "7": 1100,
    "8": 1240,
    "9": 1290,
    "10": 1340,
    "11": 1390,
    "12": 1440,
    "13": 1490,
    "14": 1540,
    "15": 1590,
    "16": 1640,
    "17": 1690,
    "18": 1740,
    "19": 1790,
    "20": 1840,
    "21": 1890,
    "22": 1940,
    "23": 1990,
    "24": 2040,
    "25": 2090,
    "26": 2140,
    "27": 2190,
    "28": 2240,
    "29": 2290,
    "30": 2340,
    "31": 2390,
    "32": 2440,
    "33": 2490,
    "34": 2540,
    "35": 2590,
    "36": 3490,
    "37": 3490,
    "38": 3490,
    "39": 3540,
    "40": 3590,
    "41": 3640,
    "42": 3690,
    "43": 3830,
    "44": 3880,
    "45": 3930,
    "46": 3980,
    "47": 4030,
    "48": 4080,
    "49": 4130,
    "50": 4180,
    "51": 4230,
    "52": 4280,
    "53": 4330,
    "54": 4380,
    "55": 4430,
    "56": 4480,
    "57": 4530,
    "58": 4580,
    "59": 4630,
    "60": 4680
  },
  "diplomat": {
    "description": "",
    "ANY": "별도 문의"
  },
  "containerType": [
    "CONSOLE",
    "20DRY",
    "40HC"
  ],
  "delivery": "Huntsville, AL",
  "partner": "YESG2M(PLS)"
}

