{
  "links": [
    {
      "label": "OFC",
      "url": "https://www.notion.so/NEW-YORK-28ed60f8e1aa4beaacd42e8c995b1b22?pvs=4"
    },
    {
      "label": "NOTION",
      "url": "https://www.notion.so/NEW-YORK-KEYWORD-4c6a4962a0134ee99e216d737948f4c5?pvs=4"
    }
  ],
  "nonDiplomat": {
    "1": 1080,
    "2": 1224,
    "3": 1368,
    "4": 1512,
    "5": 1656,
    "6": 1800,
    "7": 1944,
    "8": 2088,
    "9": 2232,
    "10": 2376,
    "11": 2520,
    "12": 2664,
    "13": 2808,
    "14": 2952,
    "15": 3096,
    "16": 3240,
    "17": 3384,
    "18": 3528,
    "19": 3672,
    "20": 3816,
    "21": 3960,
    "22": 4104,
    "23": 4248,
    "24": 4392,
    "25": 4536,
    "26": 4680,
    "27": 4824,
    "28": 4968,
    "29": 5112,
    "30": 5256,
    "31": 5400,
    "32": 5544,
    "33": 5688,
    "34": 5832,
    "35": 5976,
    "36": 6120,
    "37": 6264,
    "38": 6408,
    "39": 6552,
    "40": 6696,
    "41": 6840,
    "42": 6984,
    "43": 7128,
    "44": 7272,
    "45": 7416,
    "46": 7560,
    "47": 7704,
    "48": 7848,
    "49": 7992,
    "50": 8136,
    "51": 8280,
    "52": 8424,
    "53": 8568,
    "54": 8712,
    "55": 8856,
    "56": 9000,
    "57": 9144,
    "58": 9288,
    "59": 9432,
    "60": 9576
  },
  "diplomat": {
    "1": 1080,
    "2": 1224,
    "3": 1368,
    "4": 1512,
    "5": 1656,
    "6": 1800,
    "7": 1944,
    "8": 2088,
    "9": 2232,
    "10": 2376,
    "11": 2520,
    "12": 2664,
    "13": 2808,
    "14": 2952,
    "15": 3096,
    "16": 3240,
    "17": 3384,
    "18": 3528,
    "19": 3672,
    "20": 3816,
    "21": 3960,
    "22": 4104,
    "23": 4248,
    "24": 4392,
    "25": 4536,
    "26": 4680,
    "27": 4824,
    "28": 4968,
    "29": 5112,
    "30": 5256,
    "31": 5400,
    "32": 5544,
    "33": 5688,
    "34": 5832,
    "35": 5976,
    "36": 6120,
    "37": 6264,
    "38": 6408,
    "39": 6552,
    "40": 6696,
    "41": 6840,
    "42": 6984,
    "43": 7128,
    "44": 7272,
    "45": 7416,
    "46": 7560,
    "47": 7704,
    "48": 7848,
    "49": 7992,
    "50": 8136,
    "51": 8280,
    "52": 8424,
    "53": 8568,
    "54": 8712,
    "55": 8856,
    "56": 9000,
    "57": 9144,
    "58": 9288,
    "59": 9432,
    "60": 9576
  },
  "containerType": [
    "CONSOLE",
    "20DRY",
    "40HC"
  ]
}
