{
  "links": [
    {
      "label": "업무부 문의",
      "url": "-"
    },
    {
      "label": "NOTION",
      "url": "https://www.notion.so/CANADA-TORONTO-VANCOUVER-c06dc40c2bb94570ad0f1eee2e242296?pvs=4"
    }
  ],
  "nonDiplomat": {
      "CONSOLE": {
        "1-5" : 715,
        "6-10" : 1170,
        "11-15" : 1525,
        "16-20" : 1970,
        "21-25" : 2245,
        "26-30" : 2520,
        "31-35" : 2795,
        "36-40" : 3070,
        "41-45" : 3345,
        "46-50" : 3620,
        "51-55" : 3895
      },
      "20DRY": {
        "1-5" : 2730,
        "6-10" : 3030,
        "11-15" : 3330,
        "16-20" : 3330,
        "21-25" : 3330,
        "26-30" : 3330,
        "ANY": "1-30CBM 가능"
      },
      "40HC": {
        "1-5" : 2730,
        "6-10" : 3030,
        "11-15" : 3330,
        "16-20" : 3330,
        "21-25" : 3330,
        "26-30" : 3330,
        "31-35" : 3660,
        "36-40" : 3860,
        "41-45" : 4060,
        "46-50" : 4260,
        "51-55" : 4260,
        "56-60" : 4260
      }
  },
  "diplomat": {
      "CONSOLE": {
        "ANY": "단독 컨테이너 지원"
      },
      "20DRY": {
        "1-5" : 2730,
        "6-10" : 3030,
        "11-15" : 3330,
        "16-20" : 3330,
        "21-25" : 3330,
        "26-30" : 3330,
        "ANY": "40HC 확인"
      },
      "40HC": {
        "1-5" : 2730,
        "6-10" : 3030,
        "11-15" : 3330,
        "16-20" : 3330,
        "21-25" : 3330,
        "26-30" : 3330,
        "31-35" : 3660,
        "36-40" : 3860,
        "41-45" : 4060,
        "46-50" : 4260,
        "51-55" : 4260,
        "56-60" : 4260
      }
  },
  "containerType": [
    "CONSOLE",
    "20DRY",
    "40HC"
  ]
}
