{
  "nonDiplomat": {
      "20DRY": {
          "1-5": 600,
          "6-10": 800,
          "11-15": 875,
          "16-20": 1000,
          "21-25": 1021,
          "26-30": 1051,
          "ANY": "40HC 확인"
      },
      "40HC": {
          "1-5": 600,
          "6-10": 800,
          "11-15": 875,
          "16-20": 1000,
          "21-25": 1021,
          "26-30": 1051,
          "31-35": 1150,
          "36-40": 1221,
          "41-45": 1350,
          "46-50": 1390,
          "51-55": 1430,
          "56-60": 1460
      }
  },
  "diplomat": {
      "20DRY": {
          "1-5": 600,
          "6-10": 800,
          "11-15": 875,
          "16-20": 1000,
          "21-25": 1021,
          "26-30": 1051,
          "ANY": "40HC 확인"
      },
      "40HC": {
          "1-5": 600,
          "6-10": 800,
          "11-15": 875,
          "16-20": 1000,
          "21-25": 1021,
          "26-30": 1051,
          "31-35": 1150,
          "36-40": 1221,
          "41-45": 1350,
          "46-50": 1390,
          "51-55": 1430,
          "56-60": 1460
      }
  },
  "containerType": [
    "20DRY",
    "40HC"
  ],
  "delivery": "Noida, India",
  "partner": "KNJ"
}
